synapsemonitor/__init__.py
synapsemonitor/__main__.py
synapsemonitor/actions.py
synapsemonitor/monitor.py
test/__init__.py
test/test_monitor.py
synapsemonitor-1.1.0.dist-info/LICENSE
synapsemonitor-1.1.0.dist-info/METADATA
synapsemonitor-1.1.0.dist-info/WHEEL
synapsemonitor-1.1.0.dist-info/entry_points.txt
synapsemonitor-1.1.0.dist-info/top_level.txt
synapsemonitor-1.1.0.dist-info/RECORD
