Metadata-Version: 2.1
Name: synapsemonitor
Version: 1.1.0
Summary: Monitoring of Synapse Entity changes with the use of File Views.
Home-page: https://github.com/Sage-Bionetworks/synapsemonitor
Author: Informatics & Biocomputing - Sage Bionetworks
Author-email: infobiocomp@sagebionetworks.org
License: Apache
Project-URL: Bug Tracker, https://github.com/Sage-Bionetworks/synapsemonitor/issues
Project-URL: Source Code, https://github.com/Sage-Bionetworks/synapsemonitor
Platform: any
Classifier: Development Status :: 4 - Beta
Classifier: Environment :: Console
Classifier: Intended Audience :: Science/Research
Classifier: License :: OSI Approved :: Apache Software License
Classifier: Operating System :: OS Independent
Classifier: Programming Language :: Python
Classifier: Programming Language :: Python :: 3
Classifier: Programming Language :: Python :: 3 :: Only
Classifier: Programming Language :: Python :: 3.7
Classifier: Programming Language :: Python :: 3.8
Classifier: Programming Language :: Python :: 3.9
Classifier: Topic :: Scientific/Engineering
Requires-Python: <3.10,>=3.7
License-File: LICENSE
Requires-Dist: synapseclient (>=2.5.1)
Requires-Dist: pandas (>=1.0)
